{
  "version": "3.21.1",
  "flags": {},
  "shapes": [
    {
      "label": "Brick",
      "line_color": 1,
      "fill_color": 1,
      "points": [
        [
          320.0743494423792,
          355.7620817843866
        ],
        [
          321.9330855018587,
          330.1115241635688
        ],
        [
          423.0483271375465,
          339.40520446096656
        ],
        [
          420.4460966542751,
          362.08178438661713
        ]
      ],
      "shape_type": "polygon",
      "flags": {}
    },
    {
      "label": "Brick",
      "line_color": 1,
      "fill_color": 1,
      "points": [
        [
          328.62453531598516,
          331.2267657992565
        ],
        [
          332.34200743494426,
          306.3197026022305
        ],
        [
          434.2007434944238,
          311.89591078066917
        ],
        [
          428.996282527881,
          338.6617100371747
        ]
      ],
      "shape_type": "polygon",
      "flags": {}
    },
    {
      "label": "Brick",
      "line_color": 1,
      "fill_color": 1,
      "points": [
        [
          332.71375464684013,
          303.7174721189591
        ],
        [
          334.2007434944238,
          282.5278810408922
        ],
        [
          436.0594795539034,
          288.47583643122675
        ],
        [
          433.08550185873605,
          313.3828996282528
        ]
      ],
      "shape_type": "polygon",
      "flags": {}
    },
    {
      "label": "Brick",
      "line_color": 1,
      "fill_color": 1,
      "points": [
        [
          329.36802973977694,
          281.04089219330854
        ],
        [
          328.62453531598516,
          257.9925650557621
        ],
        [
          431.97026022304834,
          263.9405204460967
        ],
        [
          427.8810408921933,
          287.36059479553904
        ]
      ],
      "shape_type": "polygon",
      "flags": {}
    },
    {
      "label": "Brick",
      "line_color": 1,
      "fill_color": 1,
      "points": [
        [
          327.5092936802974,
          256.87732342007433
        ],
        [
          329.36802973977694,
          231.59851301115242
        ],
        [
          432.71375464684013,
          238.66171003717471
        ],
        [
          430.8550185873606,
          261.3382899628253
        ]
      ],
      "shape_type": "polygon",
      "flags": {}
    },
    {
      "label": "Brick",
      "line_color": 1,
      "fill_color": 1,
      "points": [
        [
          336.0594795539034,
          222.30483271375465
        ],
        [
          338.2899628252788,
          200.0
        ],
        [
          436.0594795539034,
          208.17843866171003
        ],
        [
          434.2007434944238,
          231.2267657992565
        ]
      ],
      "shape_type": "polygon",
      "flags": {}
    },
    {
      "label": "Brick",
      "line_color": 1,
      "fill_color": 1,
      "points": [
        [
          342.0074349442379,
          198.88475836431226
        ],
        [
          344.2379182156134,
          175.09293680297398
        ],
        [
          441.63568773234203,
          184.75836431226767
        ],
        [
          441.2639405204461,
          207.43494423791822
        ]
      ],
      "shape_type": "polygon",
      "flags": {}
    },
    {
      "label": "Brick",
      "line_color": 1,
      "fill_color": 1,
      "points": [
        [
          335.8224907063197,
          173.23420074349443
        ],
        [
          339.5399628252788,
          149.81412639405204
        ],
        [
          438.796468401487,
          160.59479553903347
        ],
        [
          436.93773234200745,
          182.5278810408922
        ]
      ],
      "shape_type": "polygon",
      "flags": {}
    },
    {
      "label": "Brick",
      "line_color": 1,
      "fill_color": 1,
      "points": [
        [
          442.0074349442379,
          183.64312267657994
        ],
        [
          442.75092936802974,
          158.364312267658
        ],
        [
          547.9553903345725,
          169.51672862453532
        ],
        [
          543.1226765799256,
          194.42379182156134
        ]
      ],
      "shape_type": "polygon",
      "flags": {}
    },
    {
      "label": "Brick",
      "line_color": 1,
      "fill_color": 1,
      "points": [
        [
          439.40520446096656,
          208.17843866171003
        ],
        [
          444.2379182156134,
          182.89962825278812
        ],
        [
          546.096654275093,
          195.53903345724908
        ],
        [
          542.007434944238,
          216.35687732342006
        ]
      ],
      "shape_type": "polygon",
      "flags": {}
    },
    {
      "label": "Brick",
      "line_color": 1,
      "fill_color": 1,
      "points": [
        [
          434.2007434944238,
          238.28996282527882
        ],
        [
          434.5724907063197,
          214.12639405204462
        ],
        [
          536.8029739776952,
          221.1895910780669
        ],
        [
          534.9442379182157,
          244.23791821561338
        ]
      ],
      "shape_type": "polygon",
      "flags": {}
    },
    {
      "label": "Brick",
      "line_color": 1,
      "fill_color": 1,
      "points": [
        [
          430.1115241635688,
          264.6840148698885
        ],
        [
          432.71375464684013,
          236.43122676579927
        ],
        [
          531.2267657992566,
          245.72490706319704
        ],
        [
          533.085501858736,
          269.1449814126394
        ]
      ],
      "shape_type": "polygon",
      "flags": {}
    },
    {
      "label": "Brick",
      "line_color": 1,
      "fill_color": 1,
      "points": [
        [
          427.8810408921933,
          287.73234200743497
        ],
        [
          428.62453531598516,
          265.0557620817844
        ],
        [
          533.085501858736,
          273.97769516728624
        ],
        [
          528.996282527881,
          297.7695167286245
        ]
      ],
      "shape_type": "polygon",
      "flags": {}
    },
    {
      "label": "Brick",
      "line_color": 1,
      "fill_color": 1,
      "points": [
        [
          435.68773234200745,
          314.4981412639405
        ],
        [
          438.2899628252788,
          293.68029739776955
        ],
        [
          536.8029739776952,
          298.8847583643123
        ],
        [
          536.4312267657992,
          323.0483271375465
        ]
      ],
      "shape_type": "polygon",
      "flags": {}
    },
    {
      "label": "Brick",
      "line_color": 1,
      "fill_color": 1,
      "points": [
        [
          434.2007434944238,
          343.86617100371745
        ],
        [
          433.8289962825279,
          320.4460966542751
        ],
        [
          535.3159851301116,
          323.7918215613383
        ],
        [
          534.9442379182157,
          348.69888475836433
        ]
      ],
      "shape_type": "polygon",
      "flags": {}
    },
    {
      "label": "Brick",
      "line_color": 1,
      "fill_color": 1,
      "points": [
        [
          427.8810408921933,
          369.1449814126394
        ],
        [
          431.5985130111524,
          343.86617100371745
        ],
        [
          530.8550185873606,
          356.50557620817847
        ],
        [
          528.6245353159851,
          379.9256505576208
        ]
      ],
      "shape_type": "polygon",
      "flags": {}
    }
  ],
  "lineColor": [
    0,
    255,
    0,
    128
  ],
  "fillColor": [
    255,
    0,
    0,
    128
  ],
  "imagePath": "colorIMG_55.png",
  "imageData": 1,
  "imageHeight": 480,
  "imageWidth": 640
}