{
  "version": "4.2.9",
  "flags": {},
  "shapes": [
    {
      "label": "Brick",
      "points": [
        [
          376.43442622950823,
          362.5
        ],
        [
          389.75409836065575,
          381.1475409836066
        ],
        [
          471.72131147540983,
          320.4918032786885
        ],
        [
          456.76229508196724,
          301.6393442622951
        ]
      ],
      "group_id": 1,
      "shape_type": "polygon",
      "flags": {}
    },
    {
      "label": "Brick",
      "points": [
        [
          388.5737704918033,
          384.27049180327873
        ],
        [
          401.89344262295083,
          402.9180327868853
        ],
        [
          483.8606557377049,
          342.26229508196724
        ],
        [
          468.9016393442623,
          323.4098360655738
        ]
      ],
      "group_id": 1,
      "shape_type": "polygon",
      "flags": {}
    },
    {
      "label": "Brick",
      "points": [
        [
          360.29508196721315,
          342.672131147541
        ],
        [
          375.2049180327869,
          361.2704918032787
        ],
        [
          455.58196721311475,
          300.6639344262295
        ],
        [
          440.62295081967216,
          281.8114754098361
        ]
      ],
      "group_id": 1,
      "shape_type": "polygon",
      "flags": {}
    },
    {
      "label": "Brick",
      "points": [
        [
          343.7459016393443,
          323.8688524590164
        ],
        [
          358.65573770491807,
          342.4672131147541
        ],
        [
          439.0327868852459,
          281.8606557377049
        ],
        [
          424.0737704918033,
          263.0081967213115
        ]
      ],
      "group_id": 1,
      "shape_type": "polygon",
      "flags": {}
    },
    {
      "label": "Brick",
      "points": [
        [
          329.09836065573774,
          303.6885245901639
        ],
        [
          343.0327868852459,
          321.92622950819674
        ],
        [
          424.73770491803276,
          263.4672131147541
        ],
        [
          409.77868852459017,
          244.61475409836066
        ]
      ],
      "group_id": 1,
      "shape_type": "polygon",
      "flags": {}
    },
    {
      "label": "Brick",
      "points": [
        [
          314.2706131078224,
          285.0951374207188
        ],
        [
          329.06976744186045,
          303.276955602537
        ],
        [
          408.8032786885246,
          243.63934426229508
        ],
        [
          393.844262295082,
          224.78688524590166
        ]
      ],
      "group_id": 1,
      "shape_type": "polygon",
      "flags": {}
    },
    {
      "label": "Brick",
      "points": [
        [
          298.1174808572423,
          266.2737917130621
        ],
        [
          312.91663519128036,
          284.45560989488024
        ],
        [
          392.6501464379445,
          224.81799855463848
        ],
        [
          377.6911300445019,
          205.96553953824505
        ]
      ],
      "group_id": 1,
      "shape_type": "polygon",
      "flags": {}
    },
    {
      "label": "Brick",
      "points": [
        [
          279.58236658932714,
          247.79582366589324
        ],
        [
          295.0116009280742,
          266.35730858468673
        ],
        [
          374.12993039443154,
          207.54060324825983
        ],
        [
          360.55684454756374,
          189.21113689095125
        ]
      ],
      "group_id": 1,
      "shape_type": "polygon",
      "flags": {}
    },
    {
      "label": "Brick",
      "points": [
        [
          361.5853658536585,
          187.8048780487805
        ],
        [
          375.7351781638465,
          206.63373134891432
        ],
        [
          451.4227642276423,
          147.15447154471545
        ],
        [
          437.5,
          129.6747967479675
        ]
      ],
      "group_id": 1,
      "shape_type": "polygon",
      "flags": {}
    },
    {
      "label": "Brick",
      "points": [
        [
          378.9634146341464,
          206.60569105691056
        ],
        [
          393.95875539961884,
          224.04430045460538
        ],
        [
          469.2073170731707,
          164.02439024390245
        ],
        [
          454.5731707317073,
          146.5447154471545
        ]
      ],
      "group_id": 1,
      "shape_type": "polygon",
      "flags": {}
    },
    {
      "label": "Brick",
      "points": [
        [
          394.63258756647724,
          225.53300935264988
        ],
        [
          409.6279283319497,
          242.9716187503447
        ],
        [
          485.71428571428567,
          184.08521303258144
        ],
        [
          470.2423436640382,
          165.4720337428938
        ]
      ],
      "group_id": 1,
      "shape_type": "polygon",
      "flags": {}
    },
    {
      "label": "Brick",
      "points": [
        [
          409.3984962406015,
          244.23558897243106
        ],
        [
          424.937343358396,
          262.15538847117796
        ],
        [
          503.50877192982455,
          203.25814536340852
        ],
        [
          486.71679197994985,
          184.08521303258144
        ]
      ],
      "group_id": 1,
      "shape_type": "polygon",
      "flags": {}
    },
    {
      "label": "Brick",
      "points": [
        [
          425.3182957393484,
          263.6641604010025
        ],
        [
          439.97493734335836,
          282.5814536340852
        ],
        [
          518.922305764411,
          224.56140350877192
        ],
        [
          502.63659147869674,
          203.51378446115285
        ]
      ],
      "group_id": 1,
      "shape_type": "polygon",
      "flags": {}
    },
    {
      "label": "Brick",
      "points": [
        [
          441.7393483709273,
          281.7142857142858
        ],
        [
          456.39598997493727,
          300.63157894736844
        ],
        [
          535.34335839599,
          242.6115288220551
        ],
        [
          520.5513784461152,
          224.18546365914787
        ]
      ],
      "group_id": 1,
      "shape_type": "polygon",
      "flags": {}
    },
    {
      "label": "Brick",
      "points": [
        [
          457.78446115288216,
          302.0200501253134
        ],
        [
          472.4411027568921,
          320.93734335839605
        ],
        [
          551.3884711779448,
          262.9172932330827
        ],
        [
          536.59649122807,
          244.49122807017548
        ]
      ],
      "group_id": 1,
      "shape_type": "polygon",
      "flags": {}
    },
    {
      "label": "Brick",
      "points": [
        [
          470.9473684210526,
          323.8295739348372
        ],
        [
          485.60401002506256,
          342.74686716791985
        ],
        [
          563.9097744360902,
          286.3408521303258
        ],
        [
          549.7593984962405,
          266.3007518796993
        ]
      ],
      "group_id": 1,
      "shape_type": "polygon",
      "flags": {}
    }
  ],
  "imagePath": "colorIMG_177.png",
  "imageData": 1,
  "imageHeight": 480,
  "imageWidth": 640
}