{
  "version": "3.21.1",
  "flags": {},
  "shapes": [
    {
      "label": "Brick",
      "line_color": 1,
      "fill_color": 1,
      "points": [
        [
          318.7755102040816,
          347.7551020408163
        ],
        [
          322.4489795918367,
          322.0408163265306
        ],
        [
          425.71428571428567,
          331.4285714285714
        ],
        [
          421.63265306122446,
          356.3265306122449
        ]
      ],
      "shape_type": "polygon",
      "flags": {}
    },
    {
      "label": "Brick",
      "line_color": 1,
      "fill_color": 1,
      "points": [
        [
          320.0,
          321.2244897959183
        ],
        [
          323.265306122449,
          296.734693877551
        ],
        [
          425.3061224489796,
          303.67346938775506
        ],
        [
          423.265306122449,
          328.57142857142856
        ]
      ],
      "shape_type": "polygon",
      "flags": {}
    },
    {
      "label": "Brick",
      "line_color": 1,
      "fill_color": 1,
      "points": [
        [
          421.63265306122446,
          357.1428571428571
        ],
        [
          424.4897959183673,
          329.7959183673469
        ],
        [
          526.530612244898,
          334.69387755102036
        ],
        [
          528.5714285714286,
          358.7755102040816
        ]
      ],
      "shape_type": "polygon",
      "flags": {}
    },
    {
      "label": "Brick",
      "line_color": 1,
      "fill_color": 1,
      "points": [
        [
          422.4489795918367,
          330.204081632653
        ],
        [
          425.3061224489796,
          306.1224489795918
        ],
        [
          527.3469387755101,
          311.0204081632653
        ],
        [
          526.9387755102041,
          333.87755102040813
        ]
      ],
      "shape_type": "polygon",
      "flags": {}
    },
    {
      "label": "Brick",
      "line_color": 1,
      "fill_color": 1,
      "points": [
        [
          425.3061224489796,
          304.48979591836735
        ],
        [
          425.71428571428567,
          280.0
        ],
        [
          524.4897959183673,
          285.71428571428567
        ],
        [
          524.4897959183673,
          309.7959183673469
        ]
      ],
      "shape_type": "polygon",
      "flags": {}
    },
    {
      "label": "Brick",
      "line_color": 1,
      "fill_color": 1,
      "points": [
        [
          425.71428571428567,
          276.3265306122449
        ],
        [
          428.57142857142856,
          251.0204081632653
        ],
        [
          528.5714285714286,
          259.1836734693877
        ],
        [
          527.3469387755101,
          284.48979591836735
        ]
      ],
      "shape_type": "polygon",
      "flags": {}
    },
    {
      "label": "Brick",
      "line_color": 1,
      "fill_color": 1,
      "points": [
        [
          321.2244897959183,
          296.3265306122449
        ],
        [
          322.85714285714283,
          269.3877551020408
        ],
        [
          426.53061224489795,
          276.734693877551
        ],
        [
          425.3061224489796,
          304.0816326530612
        ]
      ],
      "shape_type": "polygon",
      "flags": {}
    },
    {
      "label": "Brick",
      "line_color": 1,
      "fill_color": 1,
      "points": [
        [
          325.65055762081784,
          270.26022304832713
        ],
        [
          327.13754646840147,
          248.3271375464684
        ],
        [
          427.13754646840147,
          252.41635687732344
        ],
        [
          427.13754646840147,
          277.69516728624535
        ]
      ],
      "shape_type": "polygon",
      "flags": {}
    },
    {
      "label": "Brick",
      "line_color": 1,
      "fill_color": 1,
      "points": [
        [
          428.62453531598516,
          251.6728624535316
        ],
        [
          430.8550185873606,
          227.1375464684015
        ],
        [
          532.3420074349442,
          235.31598513011153
        ],
        [
          529.368029739777,
          258.7360594795539
        ]
      ],
      "shape_type": "polygon",
      "flags": {}
    },
    {
      "label": "Brick",
      "line_color": 1,
      "fill_color": 1,
      "points": [
        [
          427.13754646840147,
          225.27881040892194
        ],
        [
          428.996282527881,
          202.23048327137548
        ],
        [
          529.7397769516729,
          207.43494423791822
        ],
        [
          528.6245353159851,
          232.71375464684016
        ]
      ],
      "shape_type": "polygon",
      "flags": {}
    },
    {
      "label": "Brick",
      "line_color": 1,
      "fill_color": 1,
      "points": [
        [
          428.62453531598516,
          201.48698884758366
        ],
        [
          431.2267657992565,
          177.69516728624535
        ],
        [
          531.2267657992566,
          181.78438661710038
        ],
        [
          530.1115241635688,
          204.08921933085503
        ]
      ],
      "shape_type": "polygon",
      "flags": {}
    },
    {
      "label": "Brick",
      "line_color": 1,
      "fill_color": 1,
      "points": [
        [
          430.1115241635688,
          177.69516728624535
        ],
        [
          431.5985130111524,
          152.4163568773234
        ],
        [
          535.6877323420074,
          157.24907063197026
        ],
        [
          533.085501858736,
          180.66914498141264
        ]
      ],
      "shape_type": "polygon",
      "flags": {}
    },
    {
      "label": "Brick",
      "line_color": 1,
      "fill_color": 1,
      "points": [
        [
          325.65055762081784,
          246.84014869888478
        ],
        [
          326.7657992565056,
          223.04832713754647
        ],
        [
          431.97026022304834,
          226.39405204460968
        ],
        [
          429.36802973977694,
          251.6728624535316
        ]
      ],
      "shape_type": "polygon",
      "flags": {}
    },
    {
      "label": "Brick",
      "line_color": 1,
      "fill_color": 1,
      "points": [
        [
          329.36802973977694,
          219.33085501858736
        ],
        [
          329.36802973977694,
          195.910780669145
        ],
        [
          429.73977695167287,
          201.11524163568774
        ],
        [
          428.996282527881,
          225.65055762081784
        ]
      ],
      "shape_type": "polygon",
      "flags": {}
    },
    {
      "label": "Brick",
      "line_color": 1,
      "fill_color": 1,
      "points": [
        [
          326.7657992565056,
          193.3085501858736
        ],
        [
          328.996282527881,
          168.0297397769517
        ],
        [
          428.996282527881,
          178.8104089219331
        ],
        [
          427.5092936802974,
          203.34572490706321
        ]
      ],
      "shape_type": "polygon",
      "flags": {}
    },
    {
      "label": "Brick",
      "line_color": 1,
      "fill_color": 1,
      "points": [
        [
          327.125,
          169.375
        ],
        [
          328.62453531598516,
          144.6096654275093
        ],
        [
          427.8810408921933,
          151.3011152416357
        ],
        [
          426.7657992565056,
          176.95167286245353
        ]
      ],
      "shape_type": "polygon",
      "flags": {}
    }
  ],
  "lineColor": [
    0,
    255,
    0,
    128
  ],
  "fillColor": [
    255,
    0,
    0,
    128
  ],
  "imagePath": "colorIMG_19.png",
  "imageData": 1,
  "imageHeight": 480,
  "imageWidth": 640
}